modelselect/__init__.py
modelselect/selector.py
modelselect-0.0.1.dist-info/METADATA
modelselect-0.0.1.dist-info/WHEEL
modelselect-0.0.1.dist-info/top_level.txt
modelselect-0.0.1.dist-info/RECORD
