Metadata-Version: 2.1
Name: modelselect
Version: 0.0.1
Summary: A package helps select independent variables for traditional linear regression models
Home-page: https://github.com/shoukewei/modelselect
Author: Shouke Wei
Author-email: shouke.wei@gmail.com
License: MIT License
Keywords: python,linear regression,statsmodels,model improvement,select variables,insignificant,multicollinearity
Classifier: Development Status :: 1 - Planning
Classifier: Intended Audience :: Science/Research
Classifier: Programming Language :: Python :: 3
Classifier: Operating System :: Unix
Classifier: Operating System :: MacOS :: MacOS X
Classifier: Operating System :: Microsoft :: Windows
Requires-Dist: pandas
Requires-Dist: statsmodels
